api/__ini__.py
api/__init__.py
api/debug_talk.py
api/main.py
api/money_settle.py
api/setting.py
api/base/__init__.py
api/base/http_client.py
api/base/parser.py
api/data/__init__.py
api/data/org_category/__init__.py
api/db/__init__.py
api/db/mysql_db.py
api/db/postgre_db.py
api/db/redis_db.py
api/testcases/__init__.py
api/testcases/conftest.py
api/testcases/login/__init__.py
api/testcases/login/test_login.py
api/testcases/org_category/__init__.py
api/testcases/org_category/test_org_category.py
api/utils/__init__.py
api/utils/__int__.py
api/utils/data.py
api/utils/logger.py
api/utils/read_data.py
common/__init__.py
common/plugin.py
config/__init__.py
config/config.py
test_asic_package/__init__.py
test_asic_package/api/__ini__.py
test_asic_package/api/__init__.py
test_asic_package/api/debug_talk.py
test_asic_package/api/main.py
test_asic_package/api/money_settle.py
test_asic_package/api/setting.py
test_asic_package/api/base/__init__.py
test_asic_package/api/base/http_client.py
test_asic_package/api/base/parser.py
test_asic_package/api/data/__init__.py
test_asic_package/api/data/org_category/__init__.py
test_asic_package/api/db/__init__.py
test_asic_package/api/db/mysql_db.py
test_asic_package/api/db/postgre_db.py
test_asic_package/api/db/redis_db.py
test_asic_package/api/testcases/__init__.py
test_asic_package/api/testcases/conftest.py
test_asic_package/api/testcases/login/__init__.py
test_asic_package/api/testcases/login/test_login.py
test_asic_package/api/testcases/org_category/__init__.py
test_asic_package/api/testcases/org_category/test_org_category.py
test_asic_package/api/utils/__init__.py
test_asic_package/api/utils/__int__.py
test_asic_package/api/utils/data.py
test_asic_package/api/utils/logger.py
test_asic_package/api/utils/read_data.py
test_asic_package/common/__init__.py
test_asic_package/common/plugin.py
test_asic_package/config/__init__.py
test_asic_package/config/config.py
test_asic_package/ui/__init__.py
test_asic_package/ui/base_page/BasePage.py
test_asic_package-1.0.2.dist-info/METADATA
test_asic_package-1.0.2.dist-info/WHEEL
test_asic_package-1.0.2.dist-info/top_level.txt
test_asic_package-1.0.2.dist-info/RECORD
